component/__init__.py
component/GButton/__init__.py
component/GButton/generalButton.py
component/GButton/imageButton.py
component/GFrame/__init__.py
component/GFrame/generalFrame.py
component/GLabel/__init__.py
component/GLabel/generalLabel.py
component/GLabel/imageLabel.py
component/GLabel/textLabel.py
component/GTable/__init__.py
component/GWidget/__init__.py
component/GWidget/pageWidget.py
tests/__init__.py
GscComponent-0.1.2.dist-info/LICENSE
GscComponent-0.1.2.dist-info/METADATA
GscComponent-0.1.2.dist-info/WHEEL
GscComponent-0.1.2.dist-info/top_level.txt
GscComponent-0.1.2.dist-info/RECORD
